LICENSE
MANIFEST.in
README.rst
requirements.txt
setup.py
django_treenavext.egg-info/PKG-INFO
django_treenavext.egg-info/SOURCES.txt
django_treenavext.egg-info/dependency_links.txt
django_treenavext.egg-info/requires.txt
django_treenavext.egg-info/top_level.txt
example/simpleapp/__init__.py
example/simpleapp/admin.py
example/simpleapp/forms.py
example/simpleapp/models.py
example/simpleapp/urls.py
example/simpleapp/views.py
treenavext/__init__.py
treenavext/admin.py
treenavext/forms.py
treenavext/models.py
treenavext/tests.py