Metadata-Version: 1.1
Name: django-treenavext
Version: 0.1.1
Summary: treenavext
Home-page: https://github.com/Natgeoed/django-treenavext
Author: Taha Saidi
Author-email: tsaidi@celerity.com
License: UNKNOWN
Platform: UNKNOWN
Classifier: Framework :: Django
